yh/__init__.py
yh/__main__.py
yh-0.0.2.dist-info/DESCRIPTION.rst
yh-0.0.2.dist-info/METADATA
yh-0.0.2.dist-info/RECORD
yh-0.0.2.dist-info/WHEEL
yh-0.0.2.dist-info/entry_points.txt
yh-0.0.2.dist-info/metadata.json
yh-0.0.2.dist-info/top_level.txt
