Metadata-Version: 2.0
Name: yh
Version: 0.0.2
Summary: yh!
Home-page: https://github.com/icantsayrural/yh
Author: icantsayrural
Author-email: icantsayrural@disroot.org
License: UNKNOWN
Platform: UNKNOWN
Classifier: License :: OSI Approved :: MIT License
Classifier: Operating System :: OS Independent
